MANIFEST.in
README.rst
setup.py
docs/HISTORY.txt
docs/LICENSE.GPL
docs/LICENSE.txt
izug/__init__.py
izug.ticketbox.egg-info/PKG-INFO
izug.ticketbox.egg-info/SOURCES.txt
izug.ticketbox.egg-info/dependency_links.txt
izug.ticketbox.egg-info/entry_points.txt
izug.ticketbox.egg-info/namespace_packages.txt
izug.ticketbox.egg-info/not-zip-safe
izug.ticketbox.egg-info/requires.txt
izug.ticketbox.egg-info/top_level.txt
izug/ticketbox/README.txt
izug/ticketbox/__init__.py
izug/ticketbox/adapters.py
izug/ticketbox/config.py
izug/ticketbox/configure.zcml
izug/ticketbox/export.py
izug/ticketbox/handlers.py
izug/ticketbox/indexer.py
izug/ticketbox/interfaces.py
izug/ticketbox/lawgiver.zcml
izug/ticketbox/references.py
izug/ticketbox/setuphandlers.py
izug/ticketbox/testing.py
izug/ticketbox/vocabularies.py
izug/ticketbox/workspace.py
izug/ticketbox/zip_export.py
izug/ticketbox/browser/__init__.py
izug/ticketbox/browser/configure.zcml
izug/ticketbox/browser/edit_response.pt
izug/ticketbox/browser/helper.py
izug/ticketbox/browser/response.pt
izug/ticketbox/browser/response.py
izug/ticketbox/browser/ticket_custom_header.pt
izug/ticketbox/browser/ticket_export.py
izug/ticketbox/browser/ticket_view.pt
izug/ticketbox/browser/ticket_view.py
izug/ticketbox/browser/zip_export.py
izug/ticketbox/browser/icons/icon_funktion_download.gif
izug/ticketbox/browser/icons/icon_objekt_aufgabe.gif
izug/ticketbox/browser/icons/icon_objekt_auftragsbox.gif
izug/ticketbox/browser/javascripts/overview.js
izug/ticketbox/browser/notification/__init__.py
izug/ticketbox/browser/notification/notificationform.py
izug/ticketbox/browser/notification/ticket.pt
izug/ticketbox/browser/notification/ticket_notification.py
izug/ticketbox/browser/stylesheets/ticketbox.css
izug/ticketbox/browser/tabbed/__init__.py
izug/ticketbox/browser/tabbed/base.py
izug/ticketbox/browser/tabbed/configure.zcml
izug/ticketbox/browser/tabbed/overview.pt
izug/ticketbox/browser/tabbed/overview.py
izug/ticketbox/browser/tabbed/tabs.py
izug/ticketbox/browser/tabbed/ticketboxes.py
izug/ticketbox/content/__init__.py
izug/ticketbox/content/attachment.py
izug/ticketbox/content/configure.zcml
izug/ticketbox/content/ticket.py
izug/ticketbox/content/ticketbox.py
izug/ticketbox/locales/ftw.tabbedview.pot
izug/ticketbox/locales/izug.ticketbox-manual.pot
