Metadata-Version: 1.1
Name: izug.ticketbox
Version: 4.9.0
Summary: A tracker-like task management system for plone.
Home-page: https://github.com/4teamwork/izug.ticketbox
Author: Mathias Leimgruber
Author-email: mailto:info@4teamwork.ch
License: GPL2
Keywords: ticketbox tracker ftw
Platform: UNKNOWN
Classifier: Framework :: Plone
Classifier: Framework :: Plone :: 4.2
Classifier: Framework :: Plone :: 4.3
Classifier: Programming Language :: Python
Classifier: Topic :: Software Development :: Libraries :: Python Modules
